fit_tool/__init__.py
fit_tool/base_type.py
fit_tool/data_message.py
fit_tool/definition_message.py
fit_tool/developer_field.py
fit_tool/developer_field_definition.py
fit_tool/endian.py
fit_tool/field.py
fit_tool/field_component.py
fit_tool/field_definition.py
fit_tool/fit_file.py
fit_tool/fit_file_builder.py
fit_tool/fit_file_header.py
fit_tool/generic_message.py
fit_tool/message.py
fit_tool/record.py
fit_tool/sub_field.py
fit_tool/profile/profile_type.py
fit_tool/profile/messages/accelerometer_data_message.py
fit_tool/profile/messages/activity_message.py
fit_tool/profile/messages/ant_channel_id_message.py
fit_tool/profile/messages/ant_rx_message.py
fit_tool/profile/messages/ant_tx_message.py
fit_tool/profile/messages/aviation_attitude_message.py
fit_tool/profile/messages/barometer_data_message.py
fit_tool/profile/messages/bike_profile_message.py
fit_tool/profile/messages/blood_pressure_message.py
fit_tool/profile/messages/cadence_zone_message.py
fit_tool/profile/messages/camera_event_message.py
fit_tool/profile/messages/capabilities_message.py
fit_tool/profile/messages/climb_pro_message.py
fit_tool/profile/messages/common_fields.py
fit_tool/profile/messages/connectivity_message.py
fit_tool/profile/messages/course_message.py
fit_tool/profile/messages/course_point_message.py
fit_tool/profile/messages/developer_data_id_message.py
fit_tool/profile/messages/device_info_message.py
fit_tool/profile/messages/device_settings_message.py
fit_tool/profile/messages/dive_alarm_message.py
fit_tool/profile/messages/dive_gas_message.py
fit_tool/profile/messages/dive_settings_message.py
fit_tool/profile/messages/dive_summary_message.py
fit_tool/profile/messages/event_message.py
fit_tool/profile/messages/exd_data_concept_configuration_message.py
fit_tool/profile/messages/exd_data_field_configuration_message.py
fit_tool/profile/messages/exd_screen_configuration_message.py
fit_tool/profile/messages/exercise_title_message.py
fit_tool/profile/messages/field_capabilities_message.py
fit_tool-0.9.13.dist-info/AUTHORS
fit_tool-0.9.13.dist-info/LICENSE
fit_tool-0.9.13.dist-info/METADATA
fit_tool-0.9.13.dist-info/WHEEL
fit_tool-0.9.13.dist-info/top_level.txt
fit_tool-0.9.13.dist-info/RECORD
