Metadata-Version: 2.1
Name: fit-tool
Version: 0.9.13
Summary: A library for reading and writing Garmin FIT files.
Home-page: https://bitbucket.org/stagescycling/python_fit_tool.git
Author: Matt Tucker
Author-email: mtucker@stagescycling.com
License: none
License-File: LICENSE
License-File: AUTHORS
